{
  "_fv": 34,
  "_type": "recipe",
  "definition": {
    "recipeType": "Crafting",
    "xpReward": 0.0,
    "cookingTime": 200,
    "recipeRetstackSize": 1,
    "group": "",
    "recipeShapeless": false,
    "recipeSlots": [
      {
        "value": "Items.REDSTONE"
      },
      {
        "value": "Blocks.STONE_BUTTON"
      },
      {
        "value": "Items.HEART_OF_THE_SEA"
      },
      {
        "value": "Items.IRON_INGOT"
      },
      {
        "value": "Blocks.REDSTONE_BLOCK"
      },
      {
        "value": "Items.IRON_INGOT"
      },
      {
        "value": "Items.QUARTZ"
      },
      {
        "value": "Items.QUARTZ"
      },
      {
        "value": "Items.QUARTZ"
      }
    ],
    "recipeReturnStack": {
      "value": "CUSTOM:Computer"
    },
    "name": "computer",
    "namespace": "mod"
  }
}